{
    "name": "<YOUR NAME>",
    "netlify_subdomain": "https://amazing-euclid-b565e6.netlify.com/",
    "optional_dns": "schwaaweb.com",
    "blog_post_1": {
        "title": "What’s your Sine?",
        "url": "https://medium.com/@schwaaweb/whats-your-sine-6e6a5ad74826",
        "keywords": ["Machine Learnin","Lambda School","Acoustics","DSP","python"]
    },
    "blog_post_2": {
        "title": "ESA Releases GAIA Data r2",
        "url": "https://medium.com/@schwaaweb/esa-releases-gaia-data-release-2-98f009ee1c6",
        "keywords": ["Data Science","Esa","Astrometry","Astronomy","Juypyter Notebook"]
    },
    "blog_post_3": {
        "title": "Creating Audio with Data part 1",
        "url": "https://medium.com/@schwaaweb/creating-audio-with-data-part-1-3eaa6fcd6dd9",
        "keywords": ["Data Visualization","Csound","Audio","Data Sonification"]
    },
    "my_linkedin": "<URL TO LINKEDIN>",
    "latex": "\\begin{bmatrix}\r\n9&9 \\\\ \r\n6&10 \\\\ \r\n 5&7 \r\n\\end{bmatrix}\r\n=\r\n\\begin{bmatrix}\r\n1&0&1 \\\\ \r\n0&1&1 \\\\ \r\n 0&0&1 \r\n\\end{bmatrix}\r\n\\cdot \r\n\\begin{bmatrix}\r\n4&2 \\\\ \r\n1&3 \\\\ \r\n 5&7 \r\n\\end{bmatrix}"
}
